{"cameraMode":{"drawMode":0,"name":"Shaded","section":"Shading Mode"},"sceneLighting":false,"audioPlay":false,"sceneViewState":{"m_AlwaysRefresh":false,"showFog":true,"showSkybox":true,"showFlares":true,"showImageEffects":true,"showParticleSystems":true,"showVisualEffectGraphs":true,"m_FxEnabled":false},"in2DMode":false,"pivot":{"x":489.5,"y":245.0,"z":0.0},"rotation":{"x":0.0019337506964802743,"y":-0.9980812072753906,"z":0.04494393989443779,"w":0.04284151643514633},"size":547.3894653320313,"orthographic":false}